pymodaq_plugins_horiba/__init__.py
pymodaq_plugins_horiba/utils.py
pymodaq_plugins_horiba/daq_move_plugins/__init__.py
pymodaq_plugins_horiba/daq_viewer_plugins/__init__.py
pymodaq_plugins_horiba/daq_viewer_plugins/plugins_0D/__init__.py
pymodaq_plugins_horiba/daq_viewer_plugins/plugins_1D/__init__.py
pymodaq_plugins_horiba/daq_viewer_plugins/plugins_1D/daq_1Dviewer_Labspec6TCP.py
pymodaq_plugins_horiba/daq_viewer_plugins/plugins_2D/__init__.py
pymodaq_plugins_horiba/daq_viewer_plugins/plugins_ND/__init__.py
pymodaq_plugins_horiba/hardware/__init__.py
pymodaq_plugins_horiba/hardware/horiba/__init__.py
pymodaq_plugins_horiba/hardware/horiba/labspec6.py
pymodaq_plugins_horiba/resources/VERSION
pymodaq_plugins_horiba/resources/__init__.py
pymodaq_plugins_horiba/resources/config_template.toml
pymodaq_plugins_horiba-2.0.0.dist-info/LICENSE
pymodaq_plugins_horiba-2.0.0.dist-info/METADATA
pymodaq_plugins_horiba-2.0.0.dist-info/WHEEL
pymodaq_plugins_horiba-2.0.0.dist-info/entry_points.txt
pymodaq_plugins_horiba-2.0.0.dist-info/top_level.txt
pymodaq_plugins_horiba-2.0.0.dist-info/RECORD
